airless/google/cloud/core/__init__.py
airless/google/cloud/core/operator/__init__.py
airless/google/cloud/core/operator/base.py
airless/google/cloud/core/operator/delay.py
airless/google/cloud/core/operator/redirect.py
airless/google/cloud/pubsub/__init__.py
airless/google/cloud/pubsub/hook/__init__.py
airless/google/cloud/pubsub/hook/pubsub.py
airless_google_cloud_core-0.3.0.dist-info/METADATA
airless_google_cloud_core-0.3.0.dist-info/WHEEL
airless_google_cloud_core-0.3.0.dist-info/top_level.txt
airless_google_cloud_core-0.3.0.dist-info/RECORD
