Metadata-Version: 2.4
Name: airless-google-cloud-core
Version: 0.3.0
Summary: Airless package with the main components to use airless in google cloud
License: MIT License
Project-URL: Homepage, https://github.com/astercapital/airless
Project-URL: Bug Tracker, https://github.com/astercapital/airless/issues
Requires-Python: >=3.9
Requires-Dist: google-cloud-pubsub<3.0.0,>=2.13.11
Requires-Dist: airless-core>=0.2.1
